{
    "path": {
        "PMU1": {
            "path": [
                "PMU1",
                "N13",
                "N14",
                "CC"
            ],
            "delay": 47.45
        },
        "PMU8": {
            "path": [
                "PMU8",
                "N6",
                "CC"
            ],
            "delay": 25.73
        }
    },
    "pdcs": [
        "N13",
        "N14",
        "N6",
        "CC"
    ],
    "max_latency": 80,
    "ops_applied": [],
    "topology_seed": null
}