{
    "path": {
        "PMU1": {
            "path": [
                "PMU1",
                "N25",
                "N5",
                "CC"
            ],
            "delay": 47.09
        },
        "PMU2": {
            "path": [
                "PMU2",
                "N23",
                "CC"
            ],
            "delay": 26.630000000000003
        },
        "PMU8": {
            "path": [
                "PMU8",
                "N16",
                "N4",
                "CC"
            ],
            "delay": 48.15
        }
    },
    "pdcs": [
        "N16",
        "N23",
        "N25",
        "N4",
        "N5",
        "CC"
    ],
    "max_latency": 80,
    "ops_applied": [],
    "topology_seed": null
}