{
    "path": {
        "PMU1": {
            "path": [
                "PMU1",
                "N9",
                "CC"
            ],
            "delay": 24.44
        },
        "PMU2": {
            "path": [
                "PMU2",
                "N3",
                "N10",
                "CC"
            ],
            "delay": 64.69
        },
        "PMU3": {
            "path": [
                "PMU3",
                "N11",
                "N10",
                "CC"
            ],
            "delay": 65.53999999999999
        },
        "PMU8": {
            "path": [
                "PMU8",
                "N7",
                "N5",
                "N1",
                "CC"
            ],
            "delay": 73.86000000000001
        }
    },
    "pdcs": [
        "N1",
        "N10",
        "N11",
        "N3",
        "N5",
        "N7",
        "N9",
        "CC"
    ],
    "max_latency": 80,
    "ops_applied": [
        {
            "type": "status",
            "u": "CC",
            "v": "N2",
            "before": "up",
            "after": "down"
        }
    ],
    "topology_seed": null
}